README.md
setup.cfg
setup.py
wechat_pay_sdk.egg-info/PKG-INFO
wechat_pay_sdk.egg-info/SOURCES.txt
wechat_pay_sdk.egg-info/dependency_links.txt
wechat_pay_sdk.egg-info/requires.txt
wechat_pay_sdk.egg-info/top_level.txt
wechatpay/__init__.py
wechatpay/models.py