Metadata-Version: 1.1
Name: wechat-pay-sdk
Version: 0.6
Summary: A sdk for wechat pay
Home-page: https://github.com/Narcissist1/wechat-pay
Author: Zack Ren
Author-email: m6106918@gmail.com
License: MIT
Download-URL: https://github.com/Narcissist1/wechat-pay/archive/0.1.tar.gz
Keywords: wechat,pay
Platform: UNKNOWN
